sower/__init__.py
sower/contract.py
sower/sow.py
sower/utils/__init__.py
sower/utils/fs.py
sower/utils/yaml_loader.py
sower-1.1.1.dist-info/entry_points.txt
sower-1.1.1.dist-info/top_level.txt
sower-1.1.1.dist-info/METADATA
sower-1.1.1.dist-info/DESCRIPTION.rst
sower-1.1.1.dist-info/metadata.json
sower-1.1.1.dist-info/WHEEL
sower-1.1.1.dist-info/RECORD
