Metadata-Version: 2.0
Name: sower
Version: 1.1.1
Summary: Sower "plants" directories, files and symlinks on your filesystem based on a contract you tell it.
Home-page: http://github.com/aeroxis/sower
Author: David Daniel
Author-email: davydany@aeroxis.com
License: MIT
Platform: UNKNOWN
Classifier: Development Status :: 5 - Production/Stable
Classifier: Environment :: Console
Classifier: Operating System :: POSIX :: Linux
Classifier: Operating System :: Microsoft :: Windows
Classifier: Operating System :: MacOS
Classifier: Operating System :: MacOS :: MacOS X
Classifier: Programming Language :: Python
Classifier: Programming Language :: Python :: 2
Classifier: Programming Language :: Python :: 2.7
Classifier: Programming Language :: Python :: 3
Classifier: Programming Language :: Python :: 3.3
Classifier: Programming Language :: Python :: 3.4
Classifier: Programming Language :: Python :: 3.5
Classifier: Programming Language :: Python :: 3.6
Classifier: Programming Language :: Unix Shell
Classifier: License :: OSI Approved :: MIT License
Requires-Dist: PyYAML (>=3.12)
Requires-Dist: click (>=6.7)
Requires-Dist: simplejson (>=3.10.0)
